LICENSE
MANIFEST.in
README.md
requirements.txt
setup.py
bin/kronatools/img/favicon.ico
bin/kronatools/img/favicon.uri
bin/kronatools/img/hidden.png
bin/kronatools/img/hidden.uri
bin/kronatools/img/loading.gif
bin/kronatools/img/loading.uri
bin/kronatools/img/logo-med.png
bin/kronatools/img/logo-med.uri
bin/kronatools/lib/KronaTools.pm
bin/kronatools/scripts/ktImportXML
bin/kronatools/src/krona-2.0.js
bin/mothur/mothur
bin/mothur/uchime
bin/mothur/vsearch
bin/mothur/blast/bin/blastall
bin/mothur/blast/bin/formatdb
bin/mothur/blast/bin/megablast
config/mothulity.config
config/slurm.config
js/datatables.js
js/slideshow.js
mothulity/__init__.py
mothulity/mothulity
mothulity/mothulity_dbaser
mothulity/mothulity_draw
mothulity/mothulity_fc
mothulity/utilities.py
mothulity.egg-info/PKG-INFO
mothulity.egg-info/SOURCES.txt
mothulity.egg-info/dependency_links.txt
mothulity.egg-info/requires.txt
mothulity.egg-info/top_level.txt
templates/analysis_template.sh.j2
templates/output_template.html.j2
templates/preproc_template.sh.j2
templates/venn_diagrams_template.html.j2
test_data/database/t19.align
test_data/database/t19.tax
test_data/database/t19_v3v4.align
test_data/new_run/mltp_smpl/fastq/KA1k_R1_001.fastq
test_data/new_run/mltp_smpl/fastq/KA1k_R2_001.fastq
test_data/new_run/mltp_smpl/fastq/QA1k_R1_001.fastq
test_data/new_run/mltp_smpl/fastq/QA1k_R2_001.fastq