Metadata-Version: 2.1
Name: mothulity
Version: 1.8.0
Summary: Easy-to-use tool facilitating work with Mothur.
Home-page: https://github.com/dizak/mothulity
Author: Dariusz Izak, Agnieszka Gromadka IBB PAS
Author-email: dariusz.izak@ibb.waw.pl
License: BSD
Keywords: mothur,diversity,microbial-communities,microbial-ecology,16s,16s-rrna,its,microbial,fungal,easy-to-use,
Platform: UNKNOWN
Classifier: License :: OSI Approved :: BSD License
Classifier: Operating System :: POSIX :: Linux
Classifier: Programming Language :: Python :: 2
Classifier: Programming Language :: Python :: 3.5
Classifier: Programming Language :: Python :: 3.6
Classifier: Programming Language :: Python :: 3.7
Classifier: Programming Language :: Python :: 3.8
Requires-Python: !=3.4
